<?xml version="1.0"?>
<!DOCTYPE hibernate-mapping PUBLIC "-//Hibernate/Hibernate Mapping DTD 3.0//EN"
"http://www.hibernate.org/dtd/hibernate-mapping-3.0.dtd">
<!-- Generated Jul 9, 2020 11:48:33 AM by Hibernate Tools 4.3.1 -->
<hibernate-mapping>
    <class name="pojo.Attributes" table="attributes" catalog="ultimate2" optimistic-lock="version">
        <id name="idattributes" type="java.lang.Integer">
            <column name="idattributes" />
            <generator class="identity" />
        </id>
        <property name="attribute" type="string">
            <column name="attribute" length="45" />
        </property>
        <set name="doOnActionHasAttributeses" table="do_on_action_has_attributes" inverse="true" lazy="true" fetch="select">
            <key>
                <column name="attributes_idattributes" not-null="true" />
            </key>
            <one-to-many class="pojo.DoOnActionHasAttributes" />
        </set>
    </class>
</hibernate-mapping>
