<?xml version="1.0"?>
<!DOCTYPE hibernate-mapping PUBLIC "-//Hibernate/Hibernate Mapping DTD 3.0//EN"
"http://www.hibernate.org/dtd/hibernate-mapping-3.0.dtd">
<!-- Generated Oct 3, 2019 9:57:03 AM by Hibernate Tools 4.3.1 -->
<hibernate-mapping>
    <class name="pojo.WbMUseOldOrNewStreetStatus" table="wb_m_use_old_or_new_street_status" catalog="kuliuc" optimistic-lock="version">
        <id name="wbMUseOldOrNewStreetId" type="int">
            <column name="wb_m_use_old_or_new_street_id" />
            <generator class="assigned" />
        </id>
        <property name="wbMUseOldOrNewStatus" type="java.lang.Integer">
            <column name="wb_m_use_old_or_new_status" />
        </property>
        <property name="wbMUseOldOrNewComment" type="string">
            <column name="wb_m_use_old_or_new_comment" length="20" />
        </property>
    </class>
</hibernate-mapping>
